kladr/__init__.py
kladr/actions.py
kladr/addrfield.py
kladr/app_meta.py
kladr/apps.py
kladr/fill_kladr.py
kladr/helpers.py
kladr/models.py
kladr/ui.py
kladr/version.py
kladr/management/__init__.py
kladr/management/commands/__init__.py
kladr/management/commands/fill_kladr.py
kladr/migrations/0001_initial.py
kladr/migrations/__init__.py
kladr/south_migrations/0001_initial.py
kladr/south_migrations/__init__.py
m3_kladr-2.2.0.dist-info/licenses/LICENSE
tests/__init__.py
tests/manage.py
tests/prepare_env.py
tests/settings.py
tests/shell.sh
tests/test.sh
tests/urls.py
tests/version.py
tests/core/__init__.py
tests/core/tests.py
m3_kladr-2.2.0.dist-info/METADATA
m3_kladr-2.2.0.dist-info/WHEEL
m3_kladr-2.2.0.dist-info/top_level.txt
m3_kladr-2.2.0.dist-info/RECORD
