Metadata-Version: 2.4
Name: m3-kladr
Version: 2.2.0
Summary: Классификатор адресов Российской Федерации
Home-page: https://bitbucket.org/barsgroup/m3-kladr
Author: BARS Group
Author-email: bars@bars-open.ru
License: MIT
Classifier: Intended Audience :: Developers
Classifier: Environment :: Web Environment
Classifier: Natural Language :: Russian
Classifier: Natural Language :: English
Classifier: Operating System :: OS Independent
Classifier: Programming Language :: Python
Classifier: License :: OSI Approved :: MIT License
Classifier: Development Status :: 5 - Production/Stable
License-File: LICENSE
Requires-Dist: m3-dbfpy==2.2.5
Requires-Dist: m3-core>=2.0
Requires-Dist: m3-ui>=2.0
Requires-Dist: m3-django-compatibility>=1.12.0
Dynamic: author
Dynamic: author-email
Dynamic: classifier
Dynamic: home-page
Dynamic: license
Dynamic: license-file
Dynamic: requires-dist
Dynamic: summary
